clip_ods/__init__.py
clip_ods/clip.py
clip_ods/detector.py
clip_ods/model.py
clip_ods/simple_tokenizer.py
clip_ods/utils.py
clip_ods/resources/bpe_simple_vocab_16e6.txt.gz
clip_ods/resources/zero_text_embeddings.pt
clip_ods-0.0.1rc2.dist-info/LICENSE
clip_ods-0.0.1rc2.dist-info/METADATA
clip_ods-0.0.1rc2.dist-info/WHEEL
clip_ods-0.0.1rc2.dist-info/top_level.txt
clip_ods-0.0.1rc2.dist-info/RECORD
