Metadata-Version: 2.1
Name: clip-ods
Version: 0.0.1rc2
Summary: This lib is about a simple add-on over CLIP by OpenAI for Unsupervised Object Detection (Zeroshot). You can search bounding boxes of objects using NATURAL LANGUAGE UNDERSTANDING - no classes, only text.
Home-page: UNKNOWN
Author: Alex Shonenkov
Author-email: shonenkov@phystech.edu
License: UNKNOWN
Platform: UNKNOWN
Requires-Dist: ftfy (~=5.9)
Requires-Dist: regex (~=2021.4.4)
Requires-Dist: tqdm (~=4.60.0)
Requires-Dist: torch (~=1.7.1)
Requires-Dist: torchvision (~=0.8.2)
Requires-Dist: gdown (~=3.12.2)
Requires-Dist: ensemble-boxes (~=1.0.6)
Requires-Dist: opencv-python (~=4.5.1.48)
